mipcandy/__entry__.py
mipcandy/__init__.py
mipcandy/__main__.py
mipcandy/config.py
mipcandy/evaluation.py
mipcandy/inference.py
mipcandy/layer.py
mipcandy/metrics.py
mipcandy/run.py
mipcandy/sanity_check.py
mipcandy/settings.yml
mipcandy/sliding_window.py
mipcandy/training.py
mipcandy/types.py
mipcandy/common/__init__.py
mipcandy/common/module/__init__.py
mipcandy/common/module/conv.py
mipcandy/common/module/preprocess.py
mipcandy/common/numpy/__init__.py
mipcandy/common/numpy/regressions.py
mipcandy/common/optim/__init__.py
mipcandy/common/optim/loss.py
mipcandy/common/optim/lr_scheduler.py
mipcandy/data/__init__.py
mipcandy/data/convertion.py
mipcandy/data/dataset.py
mipcandy/data/download.py
mipcandy/data/geometric.py
mipcandy/data/io.py
mipcandy/data/visualization.py
mipcandy/frontend/__init__.py
mipcandy/frontend/notion_fe.py
mipcandy/frontend/prototype.py
mipcandy/frontend/wandb_fe.py
mipcandy/presets/__init__.py
mipcandy/presets/segmentation.py
mipcandy-1.0.1.dist-info/METADATA
mipcandy-1.0.1.dist-info/WHEEL
mipcandy-1.0.1.dist-info/entry_points.txt
mipcandy-1.0.1.dist-info/licenses/LICENSE
mipcandy-1.0.1.dist-info/RECORD
