Metadata-Version: 2.4
Name: mipcandy
Version: 1.0.1
Summary: A Candy for Medical Image Processing
Project-URL: Homepage, https://mipcandy.projectneura.org
Project-URL: Documentation, https://mipcandy-docs.projectneura.org
Project-URL: Repository, https://github.com/ProjectNeura/MIPCandy
Author-email: Project Neura <central@projectneura.org>
License-Expression: Apache-2.0
License-File: LICENSE
Requires-Python: >=3.12
Requires-Dist: matplotlib
Requires-Dist: numpy
Requires-Dist: pandas
Requires-Dist: ptflops
Requires-Dist: requests
Requires-Dist: rich
Requires-Dist: simpleitk
Requires-Dist: torch
Provides-Extra: all
Requires-Dist: mipcandy-bundles; extra == 'all'
Requires-Dist: pyvista; extra == 'all'
Provides-Extra: standard
Requires-Dist: pyvista; extra == 'standard'
